nvexpo/__init__.py
nvexpo/consts.py
nvexpo/nvexpo.py
nvexpo-0.1.1.dist-info/LICENSE
nvexpo-0.1.1.dist-info/METADATA
nvexpo-0.1.1.dist-info/WHEEL
nvexpo-0.1.1.dist-info/entry_points.txt
nvexpo-0.1.1.dist-info/RECORD
