Metadata-Version: 2.1
Name: nvexpo
Version: 0.1.1
Summary: 
Home-page: https://git.kirbylife.dev/kirbylife/nvexpo
License: MIT
Keywords: cli,bash,export,env var
Author: kirbylife
Author-email: kirbylife@protonmail.com
Requires-Python: >=3.8,<4.0
Classifier: License :: OSI Approved :: MIT License
Classifier: Programming Language :: Python :: 3
Classifier: Programming Language :: Python :: 3.8
Classifier: Programming Language :: Python :: 3.9
Classifier: Programming Language :: Python :: 3.10
Classifier: Programming Language :: Python :: 3.11
Project-URL: Repository, https://git.kirbylife.dev/kirbylife/nvexpo
